<?xml version="1.0" encoding="GBK"?>
<requests>
	<request>
		<desc>AJAX初始化加点信息</desc>
		<name>djAjaxPlusPlanInfo</name>
		<model name="com.trmdj.bx.DjPlusBxBLC.djAjaxPlusInfo"/>
		<dispatch url="/maindj/bx/initPage4Ajax/initPlusPage.jsp" type="forward" on="" default="true"/>
	</request>
	<request>
		<desc>新增加点信息</desc>
		<name>djFrmInsertBxPlus</name>
		<model name="com.trmdj.bx.DjPlusBxBLC.insertPlus"/>
		<dispatch url="/maindj/businessPlan/planSuccess.jsp" type="forward" on="" default="true"/>
	</request>
	
</requests>